rmy/__init__.py
rmy/abc.py
rmy/client_async.py
rmy/client_sync.py
rmy/common.py
rmy/connection.py
rmy/server.py
rmy-0.3.dist-info/LICENSE
rmy-0.3.dist-info/METADATA
rmy-0.3.dist-info/WHEEL
rmy-0.3.dist-info/RECORD
