Metadata-Version: 2.1
Name: rmy
Version: 0.3
Summary: Stateful rpc for Python
Author: fdv1
Author-email: francois@pytek.io
Requires-Python: >=3.8,<4.0
Classifier: Programming Language :: Python :: 3
Classifier: Programming Language :: Python :: 3.8
Classifier: Programming Language :: Python :: 3.9
Classifier: Programming Language :: Python :: 3.10
Classifier: Programming Language :: Python :: 3.11
Requires-Dist: anyio (>=3.7.0,<4.0.0)
Requires-Dist: asyncstdlib (>=3.10.7,<4.0.0)
